parse_utils/__init__.py
parse_utils/page_parser.py
parse_utils-1.3.6.dist-info/LICENSE
parse_utils-1.3.6.dist-info/METADATA
parse_utils-1.3.6.dist-info/WHEEL
parse_utils-1.3.6.dist-info/top_level.txt
parse_utils-1.3.6.dist-info/RECORD
