Metadata-Version: 2.1
Name: parse-utils
Version: 1.3.6
Summary: Page Parser Utils For scraping, List index update
Home-page: https://github.com/yogendratamang48/parse_utils.git
Author: Yogendra Tamang
Author-email: 48yogen@gmail.com
License: UNKNOWN
Platform: UNKNOWN
Classifier: Programming Language :: Python :: 3
Classifier: License :: OSI Approved :: MIT License
Classifier: Operating System :: OS Independent
Requires-Python: >=3.5
Requires-Dist: lxml
Requires-Dist: markdownify
